<?xml version="1.0" encoding="UTF-8"?>
<objects serializationModel="Studio.02.02.00">
	<object class="AudioFile" id="{012ab730-47f6-418c-b0c8-16ca2b7c9f79}">
		<property name="assetPath">
			<value>IndoorFootstep3.wav</value>
		</property>
		<property name="frequencyInKHz">
			<value>24</value>
		</property>
		<property name="channelCount">
			<value>2</value>
		</property>
		<property name="length">
			<value>0.79995833333333333</value>
		</property>
		<relationship name="masterAssetFolder">
			<destination>{3113cfeb-f69a-429a-9c5c-80616c9591cc}</destination>
		</relationship>
	</object>
</objects>
